tkai/__init__.py
tkai/__main__.py
tkai/commands.py
tkai/utils.py
tkai/chat/__init__.py
tkai/chat/__main__.py
tkai/chat/commands.py
tkai-0.1.1.dist-info/METADATA
tkai-0.1.1.dist-info/WHEEL
tkai-0.1.1.dist-info/RECORD
